{
	"Changes": [
		{
			"Action": "EditData",
			"Target": "spacechase0.SpaceCore/CookingRecipeOverrides",
			"Priority": "Late",
			"Entries": {
				"Salad": {
					"ProductQualifiedId": "(O)196",
					"ProductAmount": 1,
					"Ingredients": [
						{
							"Type": "ContextTag",
							"Value": "leafy_green_item",
							"Amount": 1,
							"OverrideText": "[LocalizedText 6480.flexiblecooking/i18n:Ingredient_LeafyGreenAny]",
							"OverrideTexturePath": "Maps/springobjects",
							"OverrideTextureRect": {
								"X": 160,
								"Y": 160,
								"Width": 16,
								"Height": 16
							}
						},
						{
							"Type": "ContextTag",
							"Value": "dandelion_item",
							"Amount": 1,
							"OverrideText": "[LocalizedText 6480.flexiblecooking/i18n:Indicator [EscapedText [LocalizedText Strings/Objects:Dandelion_Name]]]",
							"OverrideTexturePath": "Maps/springobjects",
							"OverrideTextureRect": {
								"X": 352,
								"Y": 0,
								"Width": 16,
								"Height": 16
							}
						},
						{
							"Type": "ContextTag",
							"Value": "vinegar_item",
							"Amount": 1,
							"OverrideText": "[LocalizedText 6480.flexiblecooking/i18n:Indicator [EscapedText [LocalizedText Strings/Objects:Vinegar_Name]]]",
							"OverrideTexturePath": "Maps/springobjects",
							"OverrideTextureRect": {
								"X": 176,
								"Y": 272,
								"Width": 16,
								"Height": 16
							}
						}
					]
				},
				"Maki Roll": {
					"ProductQualifiedId": "(O)228",
					"ProductAmount": 1,
					"Ingredients": [
						{
							"Type": "ContextTag",
							"Value": "category_fish, !fish_crab_pot",
							"Amount": 1,
							"ContextTagsRequireAll": true,
							"OverrideText": "[LocalizedText 6480.flexiblecooking/i18n:Ingredient_FishNonCrabPot]",
							"OverrideTexturePath": "Maps/springobjects",
							"OverrideTextureRect": {
								"X": 16,
								"Y": 96,
								"Width": 16,
								"Height": 16
							}
						},
						{
							"Type": "ContextTag",
							"Value": "seaweed_item",
							"Amount": 1,
							"OverrideText": "[LocalizedText 6480.flexiblecooking/i18n:Indicator [EscapedText [LocalizedText Strings/Objects:Seaweed_Name]]]",
							"OverrideTexturePath": "Maps/springobjects",
							"OverrideTextureRect": {
								"X": 128,
								"Y": 96,
								"Width": 16,
								"Height": 16
							}
						},
						{
							"Type": "ContextTag",
							"Value": "rice_item",
							"Amount": 1,
							"OverrideText": "[LocalizedText 6480.flexiblecooking/i18n:Indicator [EscapedText [LocalizedText Strings/Objects:Rice_Name]]]",
							"OverrideTexturePath": "Maps/springobjects",
							"OverrideTextureRect": {
								"X": 240,
								"Y": 272,
								"Width": 16,
								"Height": 16
							}
						}
					]
				},
				"Stir Fry": {
					"ProductQualifiedId": "(O)606",
					"ProductAmount": 1,
					"Ingredients": [
						{
							"Type": "ContextTag",
							"Value": "root_vegetable_item",
							"Amount": 1,
							"OverrideText": "[LocalizedText 6480.flexiblecooking/i18n:Ingredient_RootVegetableAny]",
							"OverrideTexturePath": "Maps/springobjects",
							"OverrideTextureRect": {
								"X": 0,
								"Y": 16,
								"Width": 16,
								"Height": 16
							}
						},
						{
							"Type": "ContextTag",
							"Value": "edible_mushroom",
							"Amount": 1,
							"OverrideText": "[LocalizedText 6480.flexiblecooking/i18n:Ingredient_EdibleMushroomAny]",
							"OverrideTexturePath": "Maps/springobjects",
							"OverrideTextureRect": {
								"X": 320,
								"Y": 256,
								"Width": 16,
								"Height": 16
							}
						},
						{
							"Type": "ContextTag",
							"Value": "leafy_green_item",
							"Amount": 1,
							"OverrideText": "[LocalizedText 6480.flexiblecooking/i18n:Ingredient_LeafyGreenAny]",
							"OverrideTexturePath": "Maps/springobjects",
							"OverrideTextureRect": {
								"X": 160,
								"Y": 160,
								"Width": 16,
								"Height": 16
							}
						},
						{
							"Type": "ContextTag",
							"Value": "cooking_oil_item",
							"Amount": 1,
							"OverrideText": "[LocalizedText 6480.flexiblecooking/i18n:Ingredient_OilAny]",
							"OverrideTexturePath": "Maps/springobjects",
							"OverrideTextureRect": {
								"X": 112,
								"Y": 160,
								"Width": 16,
								"Height": 16
							}
						}
					]
				}
			}
		}
	]
}